{"_colCheckBox":null,"_colCardNumber":"wDKpupmkq0yjQzHtORZBkA","_colLastName":"\u0412\u043E\u0432\u043A","_colFirstName":"\u0413\u0430\u043B\u0438\u043D\u0430","_colMiddleName":"\u041E\u043B\u0435\u043A\u0441\u0456\u0457\u0432\u043D\u0430","_colBirthDay":"1987-06-09T00:00:00","_colAge":36,"_colAddress":"\u0432\u0443\u043B. \u041F\u0448\u0435\u043D\u0438\u0447\u043D\u0430, 42","_colProfession":"\u041F\u0441\u0438\u0445\u043E\u043B\u043E\u0433 \u0437 \u0430\u0434\u0430\u043F\u0442\u0430\u0446\u0456\u0457 \u0434\u043E \u043D\u043E\u0432\u043E\u0457 \u0440\u0435\u0430\u043B\u044C\u043D\u043E\u0441\u0442\u0456","_colHospitalDate":"2021-09-04T00:00:00","_colLeaveDate":"2023-07-19T00:00:00","_fieldClaims":[""],"_fieldEntrDiagnosis":"","_fieldFinalDiagnosis":"","_fieldComplication":"","_fieldAdditionalDiagnosis":"","_fieldMKX":"","_fieldOperationName":"","_fieldOperationDate":"2024-06-05T01:29:00.9919755+02:00","_fieldChemotherapy":"","_fieldChemotherapyDate":"2024-06-05T01:29:00.9919782+02:00","_fieldHistology":"","_fieldDoctor":"","_fieldDepartmentHead":"","_fieldDepartHeadAssistant":"","_fieldOverallItem1":0,"_fieldOverallItem2":0,"_fieldOverallItem3":0,"_fieldOverallItem4":0,"_fieldOverallItem5":0,"_fieldOverallItem6":0,"_fieldOverallItem7":"\u041D\u0435 \u0437\u0431\u0456\u043B\u044C\u0448\u0435\u043D\u0430","_fieldOverallItem8":0,"_fieldOverallItem9_1":false,"_fieldOverallItem9_2":false,"_fieldOverallItem10":[],"_fieldOverallItem11":0,"_fieldOverallItem12":"","_fieldOverallItem13":0,"_fieldOverallItem14":[],"_fieldOverallItem15":0,"_fieldAnamnesisItem1":"","_fieldAnamnesisItem2":"","_fieldAnamnesisItem3":"","_fieldAnamnesisItem4":"","_fieldAnamnesisItem5":"","_fieldAnamnesisItem6":"","_fieldAnamnesisItem7":"","_fieldAnamnesisItem8":"","_fieldAnamnesisItem9":"","_fieldAnamnesisItem10":"","_fieldAnamnesisItem11":"","_fieldLifeAnamnesisItem1":"\u041D\u0435 \u0445\u043E\u0432\u0440\u0456\u0432","_fieldLifeAnamnesisItem2":"\u041D\u0435 \u0445\u043E\u0432\u0440\u0456\u0432","_fieldLifeAnamnesisItem3":"\u041D\u0435 \u0445\u043E\u0432\u0440\u0456\u0432","_fieldLifeAnamnesisItem4":"\u041D\u0435 \u0445\u043E\u0432\u0440\u0456\u0432","_fieldLifeAnamnesisItem5":"\u041D\u0435 \u0445\u043E\u0432\u0440\u0456\u0432","_fieldLifeAnamnesisItem6":"\u041D\u0435 \u0445\u043E\u0432\u0440\u0456\u0432","_fieldLifeAnamnesisItem7":"","_fieldLifeAnamnesisItem8":0,"_fieldLifeAnamnesisItem9":0,"_fieldLifeAnamnesisItem10":"","_fieldLocusMorbiItem1":[""],"_fieldLocusMorbiItem2":[""],"_fieldLocusMorbiItem3":false,"_fieldLocusMorbiItem4":[""],"_fieldLocusMorbiItem5":false,"_fieldLocusMorbiItem6":[""],"_fieldLocusMorbiItem7":[""]}
